ford/__init__.py
ford/__main__.py
ford/_markdown.py
ford/_typing.py
ford/_version.py
ford/console.py
ford/external_project.py
ford/favicon.png
ford/fixed2free2.py
ford/fortran_project.py
ford/graphs.py
ford/intrinsics.py
ford/md_admonition.py
ford/md_environ.py
ford/md_striped_table.py
ford/output.py
ford/pagetree.py
ford/reader.py
ford/settings.py
ford/sourceform.py
ford/tipue_search.py
ford/utils.py
ford/version.py
ford/css/brands.css
ford/css/brands.min.css
ford/css/fontawesome.css
ford/css/fontawesome.min.css
ford/css/local.css
ford/css/pygments.css
ford/css/regular.css
ford/css/regular.min.css
ford/css/solid.css
ford/css/solid.min.css
ford/css/v4-font-face.css
ford/css/v4-font-face.min.css
ford/css/v4-shims.css
ford/css/v4-shims.min.css
ford/js/svg-pan-zoom.min.js
ford/js/MathJax-config/.gitignore
ford/search/load_search.js
ford/templates/absint_list.html
ford/templates/base.html
ford/templates/block_list.html
ford/templates/block_page.html
ford/templates/file_list.html
ford/templates/file_page.html
ford/templates/genint_page.html
ford/templates/index.html
ford/templates/info_page.html
ford/templates/macros.html
ford/templates/mod_list.html
ford/templates/mod_page.html
ford/templates/namelist_list.html
ford/templates/namelist_page.html
ford/templates/nongenint_page.html
ford/templates/proc_list.html
ford/templates/proc_page.html
ford/templates/prog_list.html
ford/templates/prog_page.html
ford/templates/search.html
ford/templates/type_page.html
ford/templates/types_list.html
ford/webfonts/fa-brands-400.ttf
ford/webfonts/fa-brands-400.woff2
ford/webfonts/fa-regular-400.ttf
ford/webfonts/fa-regular-400.woff2
ford/webfonts/fa-solid-900.ttf
ford/webfonts/fa-solid-900.woff2
ford/webfonts/fa-v4compatibility.ttf
ford/webfonts/fa-v4compatibility.woff2
ford-7.0.10.dist-info/licenses/LICENSE
ford-7.0.10.dist-info/METADATA
ford-7.0.10.dist-info/WHEEL
ford-7.0.10.dist-info/entry_points.txt
ford-7.0.10.dist-info/top_level.txt
ford-7.0.10.dist-info/RECORD
