Metadata-Version: 2.4
Name: FORD
Version: 7.0.10
Summary: FORD (FORtran Documenter) is an automatic documentation generator for modern Fortran programs.
Author-email: Chris MacMackin <cmacmackin@gmail.com>, Peter Hill <peter.hill@york.ac.uk>
License: GPLv3
Project-URL: Source, https://github.com/Fortran-FOSS-Programmers/ford
Project-URL: Tracker, https://github.com/Fortran-FOSS-Programmers/ford/issues
Project-URL: Documentation, https://forddocs.readthedocs.io/en/latest/
Keywords: Markdown,Fortran,documentation,comments
Classifier: Development Status :: 5 - Production/Stable
Classifier: Intended Audience :: Developers
Classifier: Topic :: Software Development :: Documentation
Classifier: Topic :: Text Processing :: Markup :: HTML
Classifier: Topic :: Documentation
Classifier: Topic :: Utilities
Classifier: License :: OSI Approved :: GNU General Public License v3 (GPLv3)
Classifier: Programming Language :: Python
Classifier: Programming Language :: Python :: 3
Classifier: Programming Language :: Python :: 3.8
Classifier: Programming Language :: Python :: 3.9
Classifier: Programming Language :: Python :: 3.10
Classifier: Programming Language :: Python :: 3.11
Requires-Python: >=3.8
License-File: LICENSE
Requires-Dist: markdown~=3.4.0
Requires-Dist: markdown-include~=0.7.0
Requires-Dist: python-markdown-math~=0.8
Requires-Dist: toposort~=1.7.0
Requires-Dist: jinja2>=2.11
Requires-Dist: pygments~=2.12
Requires-Dist: beautifulsoup4>=4.5.1
Requires-Dist: graphviz~=0.20.0
Requires-Dist: tqdm~=4.64.0
Requires-Dist: tomli>=1.1.0; python_version < "3.11"
Requires-Dist: rich>=12.0.0
Requires-Dist: pcpp>=1.30
Provides-Extra: docs
Requires-Dist: sphinx>=5.3; extra == "docs"
Requires-Dist: sphinx_autodoc_typehints>=1.19; extra == "docs"
Requires-Dist: sphinx-book-theme>=0.4.0rc1; extra == "docs"
Requires-Dist: sphinx-argparse-cli>=1.10.0; extra == "docs"
Requires-Dist: sphinx-inline-tabs; extra == "docs"
Provides-Extra: tests
Requires-Dist: pytest>=3.3.0; extra == "tests"
Requires-Dist: tomli-w>=1.0.0; extra == "tests"
Dynamic: license-file
